eigenpip/__init__.py
eigenpip/eigen/.hgeol
eigenpip/eigen/.hgignore
eigenpip/eigen/CMakeLists.txt
eigenpip/eigen/COPYING.BSD
eigenpip/eigen/COPYING.GPL
eigenpip/eigen/COPYING.LGPL
eigenpip/eigen/COPYING.MINPACK
eigenpip/eigen/COPYING.MPL2
eigenpip/eigen/COPYING.README
eigenpip/eigen/CTestConfig.cmake
eigenpip/eigen/CTestCustom.cmake.in
eigenpip/eigen/INSTALL
eigenpip/eigen/README.md
eigenpip/eigen/eigen3.pc.in
eigenpip/eigen/signature_of_eigen3_matrix_library
eigenpip/eigen/Eigen/CMakeLists.txt
eigenpip/eigen/Eigen/Cholesky
eigenpip/eigen/Eigen/CholmodSupport
eigenpip/eigen/Eigen/Core
eigenpip/eigen/Eigen/Dense
eigenpip/eigen/Eigen/Eigen
eigenpip/eigen/Eigen/Eigenvalues
eigenpip/eigen/Eigen/Geometry
eigenpip/eigen/Eigen/Householder
eigenpip/eigen/Eigen/IterativeLinearSolvers
eigenpip/eigen/Eigen/Jacobi
eigenpip/eigen/Eigen/LU
eigenpip/eigen/Eigen/MetisSupport
eigenpip/eigen/Eigen/OrderingMethods
eigenpip/eigen/Eigen/PaStiXSupport
eigenpip/eigen/Eigen/PardisoSupport
eigenpip/eigen/Eigen/QR
eigenpip/eigen/Eigen/QtAlignedMalloc
eigenpip/eigen/Eigen/SPQRSupport
eigenpip/eigen/Eigen/SVD
eigenpip/eigen/Eigen/Sparse
eigenpip/eigen/Eigen/SparseCholesky
eigenpip/eigen/Eigen/SparseCore
eigenpip/eigen/Eigen/SparseLU
eigenpip/eigen/Eigen/SparseQR
eigenpip/eigen/Eigen/StdDeque
eigenpip/eigen/Eigen/StdList
eigenpip/eigen/Eigen/StdVector
eigenpip/eigen/Eigen/SuperLUSupport
eigenpip/eigen/Eigen/UmfPackSupport
eigenpip/eigen/Eigen/src/Cholesky/LDLT.h
eigenpip/eigen/Eigen/src/Cholesky/LLT.h
eigenpip/eigen/Eigen/src/Cholesky/LLT_LAPACKE.h
eigenpip/eigen/Eigen/src/CholmodSupport/CholmodSupport.h
eigenpip/eigen/Eigen/src/Core/Array.h
eigenpip/eigen/Eigen/src/Core/ArrayBase.h
eigenpip/eigen/Eigen/src/Core/ArrayWrapper.h
eigenpip/eigen/Eigen/src/Core/Assign.h
eigenpip/eigen/Eigen/src/Core/AssignEvaluator.h
eigenpip/eigen/Eigen/src/Core/Assign_MKL.h
eigenpip/eigen/Eigen/src/Core/BandMatrix.h
eigenpip/eigen/Eigen/src/Core/Block.h
eigenpip/eigen/Eigen/src/Core/BooleanRedux.h
eigenpip-0.1.0.dist-info/METADATA
eigenpip-0.1.0.dist-info/WHEEL
eigenpip-0.1.0.dist-info/top_level.txt
eigenpip-0.1.0.dist-info/RECORD
