Metadata-Version: 2.1
Name: eigenpip
Version: 0.1.0
Summary: Eigen Library for Python Linking
Home-page: http://github.com/mohanwu/eigenpip
Author: Mohan Wu, Martin Lysy
Author-email: mhwu@uwaterloo.ca
License: UNKNOWN
Platform: UNKNOWN
